0_core_client-1.1.0a8.dist-info/DESCRIPTION.rst
0_core_client-1.1.0a8.dist-info/METADATA
0_core_client-1.1.0a8.dist-info/RECORD
0_core_client-1.1.0a8.dist-info/WHEEL
0_core_client-1.1.0a8.dist-info/metadata.json
0_core_client-1.1.0a8.dist-info/top_level.txt
zeroos/__init__.py
zeroos/core0/__init__.py
zeroos/core0/client/__init__.py
zeroos/core0/client/client.py
zeroos/core0/client/typchk.py
