Metadata-Version: 1.0
Name: 0-core-client
Version: 1.1.0a8
Summary: Zero-OS 0-core client
Home-page: https://github.com/zero-os/0-core
Author: Muhamad Azmy
Author-email: muhamada@greenitglobe.com
License: Apache 2.0
Platform: UNKNOWN
